{
  "indexes": [
    {
      "collectionGroup": "chats",
      "queryScope": "COLLECTION",
      "fields": [
        {
          "fieldPath": "userIds",
          "arrayConfig": "CONTAINS"
        },
        {
          "fieldPath": "updatedAt",
          "order": "ASCENDING"
        }
      ]
    },
    {
      "collectionGroup": "messages",
      "queryScope": "COLLECTION",
      "fields": [
        {
          "fieldPath": "chatId",
          "order": "ASCENDING"
        },
        {
          "fieldPath": "createdAt",
          "order": "ASCENDING"
        }
      ]
    }
  ],
  "fieldOverrides": []
}
